gidlogger/__init__.py
gidlogger/formatter.py
gidlogger/logger_functions.py
gidlogger/logging_provider.py
gidlogger/data/__init__.py
gidlogger/data/all_timezones_data.json
gidlogger/data/capitals.json
gidlogger/data/mod_capitals.json
gidlogger/data/quick_timezones_data.json
gidlogger/utility/__init__.py
gidlogger/utility/config.py
gidlogger/utility/debug_helper.py
gidlogger/utility/misc.py
gidlogger/utility/timestuff.py
gidlogger/utility/stubs/__init__.py
gidlogger/utility/stubs/appdata_provider.pyi
gidlogger/utility/stubs/appdata_storager.pyi
gidlogger/utility/stubs/exceptions.pyi
gidlogger/utility/stubs/skeleton_tree.pyi
gidlogger-0.1.43.dist-info/LICENSE
gidlogger-0.1.43.dist-info/WHEEL
gidlogger-0.1.43.dist-info/METADATA
gidlogger-0.1.43.dist-info/RECORD
