Metadata-Version: 2.1
Name: gidlogger
Version: 0.1.43
Summary: custom logging function from Giddi
Home-page: UNKNOWN
License: UNKNOWN
Author: Giddius
Classifier: License :: OSI Approved :: MIT License
Requires-Dist: pytz
